signax/__init__.py
signax/module.py
signax/py.typed
signax/signatures.py
signax/tensor_ops.py
signax/utils.py
signax/_compat/__init__.py
signax/_compat/typing.py
signax-0.2.1.dist-info/METADATA
signax-0.2.1.dist-info/WHEEL
signax-0.2.1.dist-info/licenses/LICENSE
signax-0.2.1.dist-info/RECORD
