Metadata-Version: 2.1
Name: signax
Version: 0.2.1
Summary: Differentiable signature calculations in JAX.
Project-URL: Homepage, https://github.com/Anh-Tong/signax
Project-URL: Bug Tracker, https://github.com/Anh-Tong/signax/issues
Project-URL: Discussions, https://github.com/Anh-Tong/signax/discussions
Project-URL: Changelog, https://github.com/Anh-Tong/signax/releases
Author-email: Anh Tong <anh.h.tong@gmail.com>
License-File: LICENSE
Classifier: Development Status :: 1 - Planning
Classifier: Intended Audience :: Developers
Classifier: Intended Audience :: Science/Research
Classifier: License :: OSI Approved :: BSD License
Classifier: Operating System :: OS Independent
Classifier: Programming Language :: Python
Classifier: Programming Language :: Python :: 3
Classifier: Programming Language :: Python :: 3 :: Only
Classifier: Programming Language :: Python :: 3.8
Classifier: Programming Language :: Python :: 3.9
Classifier: Programming Language :: Python :: 3.10
Classifier: Programming Language :: Python :: 3.11
Classifier: Topic :: Scientific/Engineering
Classifier: Typing :: Typed
Requires-Python: >=3.8
Requires-Dist: equinox
Requires-Dist: jax>=0.3.10
Requires-Dist: jaxlib
Requires-Dist: jaxtyping
Requires-Dist: typing-extensions>=3.7; python_version < '3.8'
Provides-Extra: dev
Requires-Dist: pytest-cov>=3; extra == 'dev'
Requires-Dist: pytest>=6; extra == 'dev'
Provides-Extra: docs
Requires-Dist: furo; extra == 'docs'
Requires-Dist: myst-parser>=0.13; extra == 'docs'
Requires-Dist: sphinx-book-theme>=0.1.0; extra == 'docs'
Requires-Dist: sphinx-copybutton; extra == 'docs'
Requires-Dist: sphinx>=4.0; extra == 'docs'
Provides-Extra: test
Requires-Dist: pytest-cov>=3; extra == 'test'
Requires-Dist: pytest>=6; extra == 'test'
